gaiaengine/__init__.py
gaiaengine/event_listener.py
gaiaengine/event_manager.py
gaiaengine/gaiaengine.cpython-311-i386-linux-gnu.so
gaiaengine/heightmap_camera_input.py
gaiaengine/libSDL2-2.0.so
gaiaengine/libSDL2_image-2.0.so
gaiaengine/libfreetype.so
gaiaengine/libimgui.so
gaiaengine/media_bar.py
gaiaengine/overlay.py
gaiaengine/ui_manager.py
gaiaengine/unit_selector_input.py
gaiaengine/window.py
gaiaengine/aoe/__init__.py
gaiaengine/aoe/aoe_loader.py
gaiaengine/aoe/aoe_terrain.py
gaiaengine/aoe/aoe_unit.py
gaiaengine/cpp/base_types/Component.cpp
gaiaengine/cpp/base_types/Component.h
gaiaengine/cpp/base_types/EventListener.cpp
gaiaengine/cpp/base_types/EventListener.h
gaiaengine/cpp/base_types/Manager.cpp
gaiaengine/cpp/base_types/Manager.h
gaiaengine/cpp/base_types/Manager.ipp
gaiaengine/cpp/config/imconfig_impl.h
gaiaengine/cpp/config/opengl.h
gaiaengine/cpp/config/python_bindings.cpp
gaiaengine/cpp/core/Camera.cpp
gaiaengine/cpp/core/Camera.h
gaiaengine/cpp/core/Context.cpp
gaiaengine/cpp/core/Context.h
gaiaengine/cpp/core/EventManager.cpp
gaiaengine/cpp/core/EventManager.h
gaiaengine/cpp/core/TimerManager.cpp
gaiaengine/cpp/core/TimerManager.h
gaiaengine/cpp/core/Window.cpp
gaiaengine/cpp/core/Window.h
gaiaengine/cpp/geometry_primitives/ColoredRectangles.cpp
gaiaengine/cpp/geometry_primitives/ColoredRectangles.h
gaiaengine/cpp/geometry_primitives/TexturedRectangle.cpp
gaiaengine/cpp/geometry_primitives/TexturedRectangle.h
gaiaengine/cpp/heightmap/Heightmap.cpp
gaiaengine/cpp/heightmap/Heightmap.h
gaiaengine/cpp/heightmap/HeightmapCamera.cpp
gaiaengine/cpp/heightmap/HeightmapCamera.h
gaiaengine/cpp/heightmap/HeightmapSelector.cpp
gaiaengine/cpp/heightmap/HeightmapSelector.h
gaiaengine/cpp/impostor/AnimatedUnitAsset.cpp
gaiaengine/cpp/impostor/AnimatedUnitAsset.h
gaiaengine/cpp/impostor/TargetInterface.h
gaiaengine/cpp/impostor/Unit.cpp
gaiaengine/cpp/impostor/Unit.h
gaiaengine/cpp/impostor/UnitAsset.cpp
gaiaengine-0.6.1.dist-info/METADATA
gaiaengine-0.6.1.dist-info/WHEEL
gaiaengine-0.6.1.dist-info/top_level.txt
gaiaengine-0.6.1.dist-info/RECORD
gaiaengine-0.6.1.dist-info/licenses/LICENSE
gaiaengine-0.6.1.dist-info/licenses/LICENSE.LESSER
