Metadata-Version: 2.4
Name: gaiaengine
Version: 0.6.1
Summary: Lightweight and easy-to-use Python framework for creating interactive visual simulations. The project is still in development and not ready for release
Author: Paul Vallet
Author-email: luap.vallet@gmail.com
Classifier: License :: Other/Proprietary License
License-File: LICENSE
License-File: LICENSE.LESSER
Requires-Dist: pysdl2>=0.9.8
Requires-Dist: AoE2ScenarioParser
Requires-Dist: vdf
Requires-Dist: noise
Dynamic: author
Dynamic: author-email
Dynamic: classifier
Dynamic: description
Dynamic: license-file
Dynamic: requires-dist
Dynamic: summary
